{
  "gitSyncId": "67d1a3872fb4f2700e437ea5_1c817529-5019-465a-9960-ba1bcf46d924",
  "id": "controle-de-fases-s3-airtable_inputFormatter.onDiffBold",
  "pluginId": "js-plugin",
  "pluginType": "JS",
  "unpublishedAction": {
    "actionConfiguration": {
      "encodeParamsToggle": true,
      "jsArguments": [
        {
          "name": "inputValue"
        },
        {
          "name": "originalValue"
        }
      ],
      "paginationType": "NONE",
      "timeoutInMillisecond": 10000
    },
    "collectionId": "controle-de-fases-s3-airtable_inputFormatter",
    "confirmBeforeExecute": false,
    "datasource": {
      "isAutoGenerated": false,
      "name": "UNUSED_DATASOURCE",
      "pluginId": "js-plugin"
    },
    "dynamicBindingPathList": [
      {
        "key": "body"
      }
    ],
    "executeOnLoad": false,
    "fullyQualifiedName": "inputFormatter.onDiffBold",
    "name": "onDiffBold",
    "pageId": "controle-de-fases-s3-airtable",
    "userSetOnLoad": false
  }
}