{
  "gitSyncId": "67d1a3872fb4f2700e437ea5_56a63aeb-5036-491a-bc82-929bec66ef69",
  "id": "controle-de-fases-s3_Leitura_OS_Por_RecordID",
  "pluginId": "restapi-plugin",
  "pluginType": "API",
  "unpublishedAction": {
    "actionConfiguration": {
      "autoGeneratedHeaders": [],
      "body": "",
      "bodyFormData": [],
      "encodeParamsToggle": true,
      "formData": {
        "apiContentType": "none"
      },
      "headers": [],
      "httpMethod": "GET",
      "httpVersion": "HTTP11",
      "paginationType": "NONE",
      "path": "/v0/app1uxxj9gL9otgrB/ordem_de_servico/{{this.params.recordId}}",
      "pluginSpecifiedTemplates": [
        {
          "value": true
        }
      ],
      "queryParameters": [],
      "timeoutInMillisecond": 10000
    },
    "confirmBeforeExecute": false,
    "datasource": {
      "id": "Airtable",
      "isAutoGenerated": false,
      "name": "Airtable",
      "pluginId": "restapi-plugin"
    },
    "dynamicBindingPathList": [
      {
        "key": "path"
      }
    ],
    "executeOnLoad": false,
    "name": "Leitura_OS_Por_RecordID",
    "pageId": "controle-de-fases-s3",
    "userSetOnLoad": false
  }
}