{
  "gitSyncId": "67d1a3872fb4f2700e437ea5_8a5c87d4-e3a1-4e5d-be51-b1baa7d5599f",
  "id": "controle-de-fases_Criar_Movimento_Estoque",
  "pluginId": "restapi-plugin",
  "pluginType": "API",
  "unpublishedAction": {
    "actionConfiguration": {
      "autoGeneratedHeaders": [
        {
          "key": "content-type",
          "value": "application/json"
        }
      ],
      "body": "{\n\t\t\"fields\": {{this.params.Fields}}\n}",
      "bodyFormData": [],
      "encodeParamsToggle": true,
      "formData": {
        "apiContentType": "none"
      },
      "headers": [],
      "httpMethod": "POST",
      "httpVersion": "HTTP11",
      "paginationType": "NONE",
      "path": "/v0/app1uxxj9gL9otgrB/movimento_de_estoque",
      "pluginSpecifiedTemplates": [
        {
          "value": true
        }
      ],
      "queryParameters": [],
      "timeoutInMillisecond": 10000
    },
    "confirmBeforeExecute": false,
    "datasource": {
      "id": "Airtable",
      "isAutoGenerated": false,
      "name": "Airtable",
      "pluginId": "restapi-plugin"
    },
    "dynamicBindingPathList": [
      {
        "key": "body"
      }
    ],
    "executeOnLoad": false,
    "name": "Criar_Movimento_Estoque",
    "pageId": "controle-de-fases",
    "userSetOnLoad": false
  }
}