{
  "gitSyncId": "67d1a3872fb4f2700e437ea5_8c0760c2-d0ab-4898-ab2f-a2adce33a61a",
  "id": "controle-de-fases_renderFunctions.renderAvailablePartners",
  "pluginId": "js-plugin",
  "pluginType": "JS",
  "unpublishedAction": {
    "actionConfiguration": {
      "encodeParamsToggle": true,
      "jsArguments": [],
      "paginationType": "NONE",
      "timeoutInMillisecond": 10000
    },
    "collectionId": "controle-de-fases_renderFunctions",
    "confirmBeforeExecute": false,
    "datasource": {
      "isAutoGenerated": false,
      "name": "UNUSED_DATASOURCE",
      "pluginId": "js-plugin"
    },
    "dynamicBindingPathList": [
      {
        "key": "body"
      }
    ],
    "executeOnLoad": true,
    "fullyQualifiedName": "renderFunctions.renderAvailablePartners",
    "name": "renderAvailablePartners",
    "pageId": "controle-de-fases",
    "userSetOnLoad": false
  }
}