{
  "gitSyncId": "67d1a3872fb4f2700e437ea5_f1dcd14d-6b4f-44ba-9851-e9d4e858f775",
  "id": "pagina-inicial_renderFunction.normalizeString",
  "pluginId": "js-plugin",
  "pluginType": "JS",
  "unpublishedAction": {
    "actionConfiguration": {
      "encodeParamsToggle": true,
      "jsArguments": [
        {
          "name": "value"
        }
      ],
      "paginationType": "NONE",
      "timeoutInMillisecond": 10000
    },
    "collectionId": "pagina-inicial_renderFunction",
    "confirmBeforeExecute": false,
    "datasource": {
      "isAutoGenerated": false,
      "name": "UNUSED_DATASOURCE",
      "pluginId": "js-plugin"
    },
    "dynamicBindingPathList": [
      {
        "key": "body"
      }
    ],
    "executeOnLoad": false,
    "fullyQualifiedName": "renderFunction.normalizeString",
    "name": "normalizeString",
    "pageId": "pagina-inicial",
    "userSetOnLoad": false
  }
}